pye3sm/__init__.py
pye3sm/case/__init__.py
pye3sm/case/e3sm_create_batch_case.py
pye3sm/case/e3sm_create_case.py
pye3sm/case/e3sm_rename_case.py
pye3sm/elm/__init__.py
pye3sm/elm/balancecheck/__init__.py
pye3sm/elm/balancecheck/watercheck.py
pye3sm/elm/general/__init__.py
pye3sm/elm/general/halfdegree/__init__.py
pye3sm/elm/general/halfdegree/map/__init__.py
pye3sm/elm/general/halfdegree/map/elm_map_variable_halfdegree.py
pye3sm/elm/general/halfdegree/plot/__init__.py
pye3sm/elm/general/halfdegree/plot/elm_3dtsplot_variable_halfdegree_domain.py
pye3sm/elm/general/halfdegree/plot/elm_scatterplot_variables_halfdegree.py
pye3sm/elm/general/halfdegree/plot/elm_scatterplot_variables_halfdegree_domain.py
pye3sm/elm/general/halfdegree/plot/elm_surface_plot_variable_halfdegree_domain.py
pye3sm/elm/general/halfdegree/plot/elm_ts_analysis_plot_variable_halfdegree_domain.py
pye3sm/elm/general/halfdegree/plot/elm_tsplot_total_water_storage_halfdegree_domain.py
pye3sm/elm/general/halfdegree/plot/elm_tsplot_variable_halfdegree.py
pye3sm/elm/general/halfdegree/plot/elm_tsplot_variable_halfdegree_domain.py
pye3sm/elm/general/halfdegree/save/__init__.py
pye3sm/elm/general/halfdegree/save/elm_save_variable_halfdegree.py
pye3sm/elm/general/halfdegree/stats/__init__.py
pye3sm/elm/general/halfdegree/stats/elm_calculate_spatial_correlation_halfdegree.py
pye3sm/elm/general/halfdegree/stats/elm_calculate_variable_time_series_average_halfdegree.py
pye3sm/elm/general/halfdegree/stats/elm_time_series_analysis_trend_variable_halfdegree_domain.py
pye3sm/elm/general/ne30/__init__.py
pye3sm/elm/general/ne30/h2sc_calculate_variable_time_series_average_ne30.py
pye3sm/elm/general/preprocess/__init__.py
pye3sm/elm/general/preprocess/elm_plot_gpcc_data.py
pye3sm/elm/general/preprocess/elm_prepare_dem.py
pye3sm/elm/grid/__init__.py
pye3sm/elm/grid/decompInit.py
pye3sm/elm/grid/generate_elm_grid.py
pye3sm/elm/grid/global_variable.py
pye3sm/elm/h2sc/__init__.py
pye3sm/elm/h2sc/analysis/__init__.py
pye3sm-0.1.0.dist-info/LICENSE.md
pye3sm-0.1.0.dist-info/METADATA
pye3sm-0.1.0.dist-info/WHEEL
pye3sm-0.1.0.dist-info/top_level.txt
pye3sm-0.1.0.dist-info/RECORD
