Metadata-Version: 2.1
Name: pye3sm
Version: 0.1.0
Summary: Python for E3SM.
Home-page: https://github.com/changliao1025/pye3sm
Author: Chang Liao
Author-email: chang.liao@pnnl.gov
License: custom
Keywords: Earth Science
Platform: UNKNOWN
Classifier: Development Status :: 4 - Beta
Classifier: Operating System :: OS Independent
Classifier: Intended Audience :: Science/Research
Classifier: Programming Language :: Python
Classifier: Programming Language :: Python :: 3
Classifier: Topic :: Scientific/Engineering
Classifier: Topic :: Scientific/Engineering :: Visualization
Requires-Python: >=3.6.0
Requires-Dist: numpy
Requires-Dist: matplotlib
Requires-Dist: pyearth
